


    

    

    

    

[{"categories":["category1"],"description":"","tags":["tag1","tag2"],"title":"Giovani Lo Celso","url":"https://bucciaratimes.netlify.app/posts/locelso/"},{"categories":["Argentina"],"description":"\u003cp\u003e昨シーズンはブンデスリーガ2部でプレーし、リーグとカップ戦合わせて「29試合 15ゴール 4アシスト」という結果を残してクラブの1部昇格の原動力となったニコゴンサレス。\u003c/p\u003e","tags":["argen"],"title":"Nicolás González","url":"https://bucciaratimes.netlify.app/posts/nicogonzalez/"},{"categories":["Argentina"],"description":"\u003cp\u003eCBのタレント不足を世界に露呈した18年W杯。あのCB２人のプレーは人生最高のハラスメントだったと思ってます。本当にイライラしました。\u003c/p\u003e","tags":["Argentina"],"title":"Lucas Martínez Quarta","url":"https://bucciaratimes.netlify.app/posts/quarta/"},{"categories":["Argentina"],"description":"\u003cp\u003e今回は最近個人的に推しているコロンバットに関してです。\u003c/p\u003e","tags":["Argentina"],"title":"Santiago Colombatto","url":"https://bucciaratimes.netlify.app/posts/colombatto/"}]
